PyQt5/Qt3DAnimation.abi3.so
PyQt5/Qt3DAnimation.pyi
PyQt5/Qt3DCore.abi3.so
PyQt5/Qt3DCore.pyi
PyQt5/Qt3DExtras.abi3.so
PyQt5/Qt3DExtras.pyi
PyQt5/Qt3DInput.abi3.so
PyQt5/Qt3DInput.pyi
PyQt5/Qt3DLogic.abi3.so
PyQt5/Qt3DLogic.pyi
PyQt5/Qt3DRender.abi3.so
PyQt5/Qt3DRender.pyi
PyQt5/Qt5/qsci/api/python/PyQt3D.api
PyQt5/bindings/Qt3DAnimation/Qt3DAnimation.toml
PyQt5/bindings/Qt3DAnimation/Qt3DAnimationmod.sip
PyQt5/bindings/Qt3DAnimation/qabstractanimation.sip
PyQt5/bindings/Qt3DAnimation/qabstractanimationclip.sip
PyQt5/bindings/Qt3DAnimation/qabstractchannelmapping.sip
PyQt5/bindings/Qt3DAnimation/qabstractclipanimator.sip
PyQt5/bindings/Qt3DAnimation/qabstractclipblendnode.sip
PyQt5/bindings/Qt3DAnimation/qadditiveclipblend.sip
PyQt5/bindings/Qt3DAnimation/qanimationaspect.sip
PyQt5/bindings/Qt3DAnimation/qanimationclip.sip
PyQt5/bindings/Qt3DAnimation/qanimationclipdata.sip
PyQt5/bindings/Qt3DAnimation/qanimationcliploader.sip
PyQt5/bindings/Qt3DAnimation/qanimationcontroller.sip
PyQt5/bindings/Qt3DAnimation/qanimationgroup.sip
PyQt5/bindings/Qt3DAnimation/qblendedclipanimator.sip
PyQt5/bindings/Qt3DAnimation/qchannel.sip
PyQt5/bindings/Qt3DAnimation/qchannelcomponent.sip
PyQt5/bindings/Qt3DAnimation/qchannelmapper.sip
PyQt5/bindings/Qt3DAnimation/qchannelmapping.sip
PyQt5/bindings/Qt3DAnimation/qclipanimator.sip
PyQt5/bindings/Qt3DAnimation/qclipblendnodecreatedchange.sip
PyQt5/bindings/Qt3DAnimation/qclipblendvalue.sip
PyQt5/bindings/Qt3DAnimation/qclock.sip
PyQt5/bindings/Qt3DAnimation/qkeyframe.sip
PyQt5/bindings/Qt3DAnimation/qkeyframeanimation.sip
PyQt5/bindings/Qt3DAnimation/qlerpclipblend.sip
PyQt5/bindings/Qt3DAnimation/qmorphinganimation.sip
PyQt5/bindings/Qt3DAnimation/qmorphtarget.sip
PyQt5/bindings/Qt3DAnimation/qskeletonmapping.sip
PyQt5/bindings/Qt3DAnimation/qvertexblendanimation.sip
PyQt5/bindings/Qt3DCore/Qt3DCore.toml
PyQt5/bindings/Qt3DCore/Qt3DCoremod.sip
PyQt5/bindings/Qt3DCore/qabstractaspect.sip
PyQt5/bindings/Qt3DCore/qabstractskeleton.sip
PyQt3D-5.15.7.dist-info/WHEEL
PyQt3D-5.15.7.dist-info/METADATA
PyQt3D-5.15.7.dist-info/RECORD
