Metadata-Version: 2.1
Name: PyQt3D
Version: 5.15.7
Requires-Python: >=3.8
Summary: Python bindings for the Qt 3D framework
Project-Url: homepage, https://www.riverbankcomputing.com/software/pyqt3d/
Requires-Dist: PyQt5 (>=5.15.4)
License: GPL v3
Author-Email: Riverbank Computing Limited <info@riverbankcomputing.com>
